qhist/__init__.py
qhist/decorators.py
qhist/functools.py
qhist/patching.py
qhist/styles.py
qhist/utils.py
qhist/v2/__init__.py
qhist/v2/core.py
qhist/v2/wrappers.py
qhist/v3/__init__.py
qhist/v3/anchors.py
qhist/v3/core.py
qhist/v3/lifecycle.py
qhist/v3/proto.py
qhist/v3/stats.py
qhist/v3/wrappers.py
qhist-0.1.2.dist-info/LICENSE
qhist-0.1.2.dist-info/METADATA
qhist-0.1.2.dist-info/WHEEL
qhist-0.1.2.dist-info/pbr.json
qhist-0.1.2.dist-info/top_level.txt
qhist-0.1.2.dist-info/RECORD
