Metadata-Version: 2.1
Name: qhist
Version: 0.1.2
Summary: A Quick Histogram drawer for `ROOT::TTree` for smoother HEP analysis!
Home-page: https://gitlab.com/ckhurewa/qhist
Author: Chitsanu Khurewathanakul
Author-email: chitsanu.khurewathanakul@gmail.com
License: GNU GPLv3
Platform: unix
Classifier: Development Status :: 4 - Beta
Classifier: Environment :: Console
Classifier: Intended Audience :: Developers
Classifier: Intended Audience :: Information Technology
Classifier: Operating System :: OS Independent
Classifier: Programming Language :: Python :: 2.7
Classifier: Topic :: Utilities
Requires-Python: ~=2.7
Requires-Dist: pyroot-zen
Requires-Dist: PythonCK
